llama_index/readers/joplin/__init__.py
llama_index/readers/joplin/base.py
llama_index_readers_joplin-0.5.0.dist-info/METADATA
llama_index_readers_joplin-0.5.0.dist-info/WHEEL
llama_index_readers_joplin-0.5.0.dist-info/licenses/LICENSE
llama_index_readers_joplin-0.5.0.dist-info/RECORD
