Metadata-Version: 2.4
Name: llama-index-readers-joplin
Version: 0.5.0
Summary: llama-index readers joplin integration
Author-email: Your Name <you@example.com>
Maintainer: alondmnt
License-Expression: MIT
License-File: LICENSE
Requires-Python: <4.0,>=3.9
Requires-Dist: llama-index-core<0.14,>=0.13.0
Requires-Dist: llama-index-readers-file<0.6,>=0.5.0
